<Properties StartupConfiguration="{EE57A22F-0576-446E-83CF-099C3C98FD14}|Default">
  <MonoDevelop.Ide.ItemProperties.testMonogame PreferredExecutionTarget="MonoDevelop.Default" />
  <MonoDevelop.Ide.Workbench ActiveDocument="testMonogame/KeyboardController.cs">
    <Files>
      <File FileName="testMonogame/KeyboardController.cs" Line="35" Column="41" />
      <File FileName="testMonogame/Game1.cs" Line="118" Column="31" />
      <File FileName="testMonogame/ClosedDoor.cs" />
      <File FileName="testMonogame/CaveDoor.cs" />
      <File FileName="testMonogame/Commands/QuitCommand.cs" Line="2" Column="1" />
      <File FileName="testMonogame/Commands/CycleBocksCommand.cs" Line="2" Column="1" />
      <File FileName="testMonogame/Commands/CycleItemCommand.cs" Line="17" Column="10" />
      <File FileName="testMonogame/Commands/CycleEnemyCommand.cs" Line="17" Column="10" />
    </Files>
    <Pads>
      <Pad Id="ProjectPad">
        <State name="__root__">
          <Node name="testMonogame" expanded="True">
            <Node name="testMonogame" expanded="True">
              <Node name="Commands" expanded="True" />
              <Node name="Content" expanded="True" />
              <Node name="KeyboardController.cs" selected="True" />
            </Node>
          </Node>
        </State>
      </Pad>
    </Pads>
  </MonoDevelop.Ide.Workbench>
  <MonoDevelop.Ide.DebuggingService.PinnedWatches />
  <MonoDevelop.Ide.Workspace ActiveConfiguration="Debug" />
  <MonoDevelop.Ide.DebuggingService.Breakpoints>
    <BreakpointStore />
  </MonoDevelop.Ide.DebuggingService.Breakpoints>
  <MultiItemStartupConfigurations />
</Properties>